ABuilder/ABuilder.py
ABuilder/__init__.py
ABuilder/Library/__init__.py
ABuilder/Library/builder.py
ABuilder/Library/db.py
ABuilder/Library/validate.py
a_sqlbuilder-0.0.2.dist-info/LICENSE
a_sqlbuilder-0.0.2.dist-info/METADATA
a_sqlbuilder-0.0.2.dist-info/WHEEL
a_sqlbuilder-0.0.2.dist-info/top_level.txt
a_sqlbuilder-0.0.2.dist-info/RECORD
