Metadata-Version: 2.1
Name: a-sqlbuilder
Version: 0.0.2
Summary: MySQL chained operation of Python development
Home-page: https://github.com/lizhenggan/ABuilder
Author: aiden.li
Author-email: 1334435738@qq.com
License: UNKNOWN
Platform: UNKNOWN
Classifier: License :: OSI Approved :: MIT License
Classifier: Intended Audience :: Developers
Classifier: Operating System :: OS Independent
Classifier: Programming Language :: Python
Classifier: Programming Language :: Python :: 2
Classifier: Programming Language :: Python :: 2.6
Classifier: Programming Language :: Python :: 2.7
Classifier: Programming Language :: Python :: 3
Classifier: Programming Language :: Python :: 3.3
Classifier: Programming Language :: Python :: 3.4
Classifier: Programming Language :: Python :: 3.5
Requires-Dist: pymysql (>=0.9.3)
